pycaret/__init__.py
pycaret/anomaly.py
pycaret/arules.py
pycaret/classification.py
pycaret/clustering.py
pycaret/datasets.py
pycaret/distributions.py
pycaret/nlp.py
pycaret/regression.py
pycaret/utils.py
pycaret/containers/__init__.py
pycaret/containers/base_container.py
pycaret/containers/metrics/__init__.py
pycaret/containers/metrics/anomaly.py
pycaret/containers/metrics/base_metric.py
pycaret/containers/metrics/classification.py
pycaret/containers/metrics/clustering.py
pycaret/containers/metrics/regression.py
pycaret/containers/models/__init__.py
pycaret/containers/models/anomaly.py
pycaret/containers/models/base_model.py
pycaret/containers/models/classification.py
pycaret/containers/models/clustering.py
pycaret/containers/models/regression.py
pycaret/internal/Display.py
pycaret/internal/__init__.py
pycaret/internal/cuml_wrappers.py
pycaret/internal/distributions.py
pycaret/internal/drift_report.py
pycaret/internal/logging.py
pycaret/internal/meta_estimators.py
pycaret/internal/metrics.py
pycaret/internal/persistence.py
pycaret/internal/pipeline.py
pycaret/internal/preprocess.py
pycaret/internal/tabular.py
pycaret/internal/tunable.py
pycaret/internal/utils.py
pycaret/internal/validation.py
pycaret/internal/patches/__init__.py
pycaret/internal/patches/boruta_py.py
pycaret/internal/patches/sklearn.py
pycaret/internal/patches/yellowbrick.py
pycaret/internal/plots/__init__.py
pycaret/internal/plots/helper.py
pycaret/internal/plots/residual_plots.py
pycaret/internal/plots/yellowbrick.py
pycaret/loggers/__init__.py
pycaret/loggers/base_logger.py
pycaret/loggers/mlflow_logger.py
pycaret/loggers/wandb_logger.py
pycaret/parallel/__init__.py
pycaret/parallel/fugue_backend.py
pycaret/parallel/parallel_backend.py
pycaret/tests/__init__.py
pycaret/tests/test_anomaly.py
pycaret/tests/test_arules.py
pycaret/tests/test_categorical_features.py
pycaret/tests/test_check_fairness.py
pycaret/tests/test_classification.py
pycaret/tests/test_classification_parallel.py
pycaret_nightly-2.3.10.dev1651454453.dist-info/LICENSE
pycaret_nightly-2.3.10.dev1651454453.dist-info/METADATA
pycaret_nightly-2.3.10.dev1651454453.dist-info/WHEEL
pycaret_nightly-2.3.10.dev1651454453.dist-info/top_level.txt
pycaret_nightly-2.3.10.dev1651454453.dist-info/RECORD
