Metadata-Version: 2.1
Name: pycaret-nightly
Version: 2.3.10.dev1651454453
Summary: Nightly version of PyCaret - An open source, low-code machine learning library in Python.
Home-page: https://github.com/pycaret/pycaret-nightly
Author: Moez Ali
Author-email: moez.ali@queensu.ca
License: MIT
Platform: UNKNOWN
Classifier: License :: OSI Approved :: MIT License
Classifier: Programming Language :: Python :: 3.6
Classifier: Programming Language :: Python :: 3.7
Classifier: Programming Language :: Python :: 3.8
License-File: LICENSE
Requires-Dist: pandas
Requires-Dist: scipy (<=1.5.4)
Requires-Dist: seaborn
Requires-Dist: matplotlib
Requires-Dist: IPython
Requires-Dist: joblib
Requires-Dist: scikit-learn (==0.23.2)
Requires-Dist: ipywidgets
Requires-Dist: yellowbrick (>=1.0.1)
Requires-Dist: lightgbm (>=2.3.1)
Requires-Dist: plotly (>=4.4.1)
Requires-Dist: wordcloud
Requires-Dist: textblob
Requires-Dist: cufflinks (>=0.17.0)
Requires-Dist: umap-learn
Requires-Dist: pyLDAvis
Requires-Dist: gensim (<4.0.0)
Requires-Dist: spacy (<2.4.0)
Requires-Dist: nltk
Requires-Dist: mlxtend (>=0.17.0)
Requires-Dist: pyod
Requires-Dist: pandas-profiling (>=2.8.0)
Requires-Dist: kmodes (>=0.10.1)
Requires-Dist: mlflow
Requires-Dist: imbalanced-learn (==0.7.0)
Requires-Dist: scikit-plot
Requires-Dist: Boruta
Requires-Dist: pyyaml (<6.0.0)
Requires-Dist: numba (<0.55)
Provides-Extra: full
Requires-Dist: shap ; extra == 'full'
Requires-Dist: interpret (<=0.2.4) ; extra == 'full'
Requires-Dist: tune-sklearn (>=0.2.1) ; extra == 'full'
Requires-Dist: ray[tune] (>=1.0.0) ; extra == 'full'
Requires-Dist: hyperopt ; extra == 'full'
Requires-Dist: optuna (>=2.2.0) ; extra == 'full'
Requires-Dist: scikit-optimize (>=0.8.1) ; extra == 'full'
Requires-Dist: psutil ; extra == 'full'
Requires-Dist: catboost (>=0.23.2) ; extra == 'full'
Requires-Dist: xgboost (>=1.1.0) ; extra == 'full'
Requires-Dist: explainerdashboard ; extra == 'full'
Requires-Dist: m2cgen ; extra == 'full'
Requires-Dist: evidently ; extra == 'full'
Requires-Dist: autoviz ; extra == 'full'
Requires-Dist: fairlearn ; extra == 'full'
Requires-Dist: fastapi ; extra == 'full'
Requires-Dist: uvicorn ; extra == 'full'
Requires-Dist: gradio ; extra == 'full'
Requires-Dist: fugue (>=0.6.6) ; extra == 'full'
Requires-Dist: boto3 ; extra == 'full'
Requires-Dist: azure-storage-blob ; extra == 'full'
Requires-Dist: google-cloud-storage ; extra == 'full'
Provides-Extra: test
Requires-Dist: pytest ; extra == 'test'
Requires-Dist: moto ; extra == 'test'
Requires-Dist: codecov ; extra == 'test'
Requires-Dist: dask[dataframe] ; extra == 'test'
Requires-Dist: shap ; extra == 'test'
Requires-Dist: interpret (<=0.2.4) ; extra == 'test'
Requires-Dist: tune-sklearn (>=0.2.1) ; extra == 'test'
Requires-Dist: ray[tune] (>=1.0.0) ; extra == 'test'
Requires-Dist: hyperopt ; extra == 'test'
Requires-Dist: optuna (>=2.2.0) ; extra == 'test'
Requires-Dist: scikit-optimize (>=0.8.1) ; extra == 'test'
Requires-Dist: psutil ; extra == 'test'
Requires-Dist: catboost (>=0.23.2) ; extra == 'test'
Requires-Dist: xgboost (>=1.1.0) ; extra == 'test'
Requires-Dist: explainerdashboard ; extra == 'test'
Requires-Dist: m2cgen ; extra == 'test'
Requires-Dist: evidently ; extra == 'test'
Requires-Dist: autoviz ; extra == 'test'
Requires-Dist: fairlearn ; extra == 'test'
Requires-Dist: fastapi ; extra == 'test'
Requires-Dist: uvicorn ; extra == 'test'
Requires-Dist: gradio ; extra == 'test'
Requires-Dist: fugue (>=0.6.6) ; extra == 'test'
Requires-Dist: boto3 ; extra == 'test'
Requires-Dist: azure-storage-blob ; extra == 'test'
Requires-Dist: google-cloud-storage ; extra == 'test'
